Workbook

Sheet 假设
A1: 美的集团 DCF 模型（单位：亿元；蓝色为输入假设）
A2: 项目 | B2: 数值 | C2: 依据
A3: 公司 | B3: 美的集团
A4: 基期年份 | B4: 2025
A5: 基期营业总收入 | B5: 4585.0241
A6: 基期经营性营运资本 | B6: -146.72077 | C6: 基期营运资本按「营运资本/收入」假设标准化，避免单年科目重分类造成的跳变
A7: 有效税率 | B7: 0.164 | C7: 取近 3 年均值 16.4%（2023-2025：16.2%/17.0%/16.1%）
A8: 折旧摊销 / 收入 | B8: 0.02 | C8: 取近 3 年均值 2.0%，与 6 年区间 1.8%-2.0% 一致
A9: 资本开支 / 收入 | B9: 0.02 | C9: 取近 3 年均值 2.0%（2023-2025：1.7%/1.9%/2.4%）
A10: 经营性营运资本 / 收入 | B10: -0.032 | C10: 营运资本比率波动大（-12.5% 至 +8.1%），按规则取近 3 年均值 -3.2%
A11: WACC | B11: 0.0645 | C11: CAPM 参考 WACC 6.45%（rf 1.65%、Blume 调整 Beta 0.87、ERP 6%、税后债务成本 2.41%、股权权重 90.7%）
A12: 永续增长率 | B12: 0.025 | C12: 2.5%，低于 3% 上限，考虑家电行业成熟期名义增长
A13: 有息负债 | B13: 674.80997
A14: 现金及交易性金融资产 | B14: 859.57867
A15: 少数股东权益 | B15: 132.02918
A16: 总股本（亿股） | B16: 75.97145
A17: 当前股价（元） | B17: 86.54

Sheet 预测
A1: 自由现金流预测（FCFF）
A2: 年份 | B2: 2026 | C2: 2027 | D2: 2028 | E2: 2029 | F2: 2030
A3: 期数 t | B3: 1 | C3: 2 | D3: 3 | E3: 4 | F3: 5
A4: 收入增速 | B4: 0.07 | C4: 0.06 | D4: 0.05 | E4: 0.045 | F4: 0.04
A5: EBIT 利润率 | B5: 0.1 | C5: 0.1 | D5: 0.1 | E5: 0.1 | F5: 0.1
A6: 营业总收入 | B6: =假设!$B$5*(1+B4) | C6: =B6*(1+C4) | D6: =C6*(1+D4) | E6: =D6*(1+E4) | F6: =E6*(1+F4)
A7: EBIT | B7: =B6*B5 | C7: =C6*C5 | D7: =D6*D5 | E7: =E6*E5 | F7: =F6*F5
A8: NOPAT = EBIT×(1−税率) | B8: =B7*(1-假设!$B$7) | C8: =C7*(1-假设!$B$7) | D8: =D7*(1-假设!$B$7) | E8: =E7*(1-假设!$B$7) | F8: =F7*(1-假设!$B$7)
A9: 折旧摊销 | B9: =B6*假设!$B$8 | C9: =C6*假设!$B$8 | D9: =D6*假设!$B$8 | E9: =E6*假设!$B$8 | F9: =F6*假设!$B$8
A10: 资本开支 | B10: =B6*假设!$B$9 | C10: =C6*假设!$B$9 | D10: =D6*假设!$B$9 | E10: =E6*假设!$B$9 | F10: =F6*假设!$B$9
A11: 经营性营运资本 | B11: =B6*假设!$B$10 | C11: =C6*假设!$B$10 | D11: =D6*假设!$B$10 | E11: =E6*假设!$B$10 | F11: =F6*假设!$B$10
A12: 营运资本变动 ΔNWC | B12: =B11-假设!$B$6 | C12: =C11-B11 | D12: =D11-C11 | E12: =E11-D11 | F12: =F11-E11
A13: FCFF | B13: =B8+B9-B10-B12 | C13: =C8+C9-C10-C12 | D13: =D8+D9-D10-D12 | E13: =E8+E9-E10-E12 | F13: =F8+F9-F10-F12
A14: 折现因子 | B14: =1/(1+假设!$B$11)^B3 | C14: =1/(1+假设!$B$11)^C3 | D14: =1/(1+假设!$B$11)^D3 | E14: =1/(1+假设!$B$11)^E3 | F14: =1/(1+假设!$B$11)^F3
A15: FCFF 现值 | B15: =B13*B14 | C15: =C13*C14 | D15: =D13*D14 | E15: =E13*E14 | F15: =F13*F14

Sheet 估值
A1: 估值汇总
A3: 预测期 FCFF 现值合计 | B3: =SUM(预测!B15:F15)
A4: 终值（戈登增长） | B4: =预测!F13*(1+假设!B12)/(假设!B11-假设!B12)
A5: 终值现值 | B5: =B4/(1+假设!B11)^5
A6: 企业价值 EV | B6: =B3+B5
A7: 减：有息负债 | B7: =假设!B13
A8: 加：现金 | B8: =假设!B14
A9: 减：少数股东权益 | B9: =假设!B15
A10: 股权价值 | B10: =B6-B7+B8-B9
A11: 每股价值（元） | B11: =B10/假设!B16
A12: 当前股价（元） | B12: =假设!B17
A13: 相对现价 | B13: =B11/B12-1
A14: 终值占 EV 比重 | B14: =B5/B6

Sheet 敏感性
A1: 每股价值敏感性（行：WACC，列：永续增长率）
A4: WACC \ g | B4: 0.015 | C4: 0.02 | D4: 0.025 | E4: 0.03 | F4: 0.035
A5: 0.0545 | B5: =(SUMPRODUCT(预测!$B$13:$F$13/(1+$A5)^预测!$B$3:$F$3)+预测!$F$13*(1+B$4)/($A5-B$4)/(1+$A5)^5-假设!$B$13+假设!$B$14-假设!$B$15)/假设!$B$16 | C5: =(SUMPRODUCT(预测!$B$13:$F$13/(1+$A5)^预测!$B$3:$F$3)+预测!$F$13*(1+C$4)/($A5-C$4)/(1+$A5)^5-假设!$B$13+假设!$B$14-假设!$B$15)/假设!$B$16 | D5: =(SUMPRODUCT(预测!$B$13:$F$13/(1+$A5)^预测!$B$3:$F$3)+预测!$F$13*(1+D$4)/($A5-D$4)/(1+$A5)^5-假设!$B$13+假设!$B$14-假设!$B$15)/假设!$B$16 | E5: =(SUMPRODUCT(预测!$B$13:$F$13/(1+$A5)^预测!$B$3:$F$3)+预测!$F$13*(1+E$4)/($A5-E$4)/(1+$A5)^5-假设!$B$13+假设!$B$14-假设!$B$15)/假设!$B$16 | F5: =(SUMPRODUCT(预测!$B$13:$F$13/(1+$A5)^预测!$B$3:$F$3)+预测!$F$13*(1+F$4)/($A5-F$4)/(1+$A5)^5-假设!$B$13+假设!$B$14-假设!$B$15)/假设!$B$16
A6: 0.0595 | B6: =(SUMPRODUCT(预测!$B$13:$F$13/(1+$A6)^预测!$B$3:$F$3)+预测!$F$13*(1+B$4)/($A6-B$4)/(1+$A6)^5-假设!$B$13+假设!$B$14-假设!$B$15)/假设!$B$16 | C6: =(SUMPRODUCT(预测!$B$13:$F$13/(1+$A6)^预测!$B$3:$F$3)+预测!$F$13*(1+C$4)/($A6-C$4)/(1+$A6)^5-假设!$B$13+假设!$B$14-假设!$B$15)/假设!$B$16 | D6: =(SUMPRODUCT(预测!$B$13:$F$13/(1+$A6)^预测!$B$3:$F$3)+预测!$F$13*(1+D$4)/($A6-D$4)/(1+$A6)^5-假设!$B$13+假设!$B$14-假设!$B$15)/假设!$B$16 | E6: =(SUMPRODUCT(预测!$B$13:$F$13/(1+$A6)^预测!$B$3:$F$3)+预测!$F$13*(1+E$4)/($A6-E$4)/(1+$A6)^5-假设!$B$13+假设!$B$14-假设!$B$15)/假设!$B$16 | F6: =(SUMPRODUCT(预测!$B$13:$F$13/(1+$A6)^预测!$B$3:$F$3)+预测!$F$13*(1+F$4)/($A6-F$4)/(1+$A6)^5-假设!$B$13+假设!$B$14-假设!$B$15)/假设!$B$16
A7: 0.0645 | B7: =(SUMPRODUCT(预测!$B$13:$F$13/(1+$A7)^预测!$B$3:$F$3)+预测!$F$13*(1+B$4)/($A7-B$4)/(1+$A7)^5-假设!$B$13+假设!$B$14-假设!$B$15)/假设!$B$16 | C7: =(SUMPRODUCT(预测!$B$13:$F$13/(1+$A7)^预测!$B$3:$F$3)+预测!$F$13*(1+C$4)/($A7-C$4)/(1+$A7)^5-假设!$B$13+假设!$B$14-假设!$B$15)/假设!$B$16 | D7: =(SUMPRODUCT(预测!$B$13:$F$13/(1+$A7)^预测!$B$3:$F$3)+预测!$F$13*(1+D$4)/($A7-D$4)/(1+$A7)^5-假设!$B$13+假设!$B$14-假设!$B$15)/假设!$B$16 | E7: =(SUMPRODUCT(预测!$B$13:$F$13/(1+$A7)^预测!$B$3:$F$3)+预测!$F$13*(1+E$4)/($A7-E$4)/(1+$A7)^5-假设!$B$13+假设!$B$14-假设!$B$15)/假设!$B$16 | F7: =(SUMPRODUCT(预测!$B$13:$F$13/(1+$A7)^预测!$B$3:$F$3)+预测!$F$13*(1+F$4)/($A7-F$4)/(1+$A7)^5-假设!$B$13+假设!$B$14-假设!$B$15)/假设!$B$16
A8: 0.0695 | B8: =(SUMPRODUCT(预测!$B$13:$F$13/(1+$A8)^预测!$B$3:$F$3)+预测!$F$13*(1+B$4)/($A8-B$4)/(1+$A8)^5-假设!$B$13+假设!$B$14-假设!$B$15)/假设!$B$16 | C8: =(SUMPRODUCT(预测!$B$13:$F$13/(1+$A8)^预测!$B$3:$F$3)+预测!$F$13*(1+C$4)/($A8-C$4)/(1+$A8)^5-假设!$B$13+假设!$B$14-假设!$B$15)/假设!$B$16 | D8: =(SUMPRODUCT(预测!$B$13:$F$13/(1+$A8)^预测!$B$3:$F$3)+预测!$F$13*(1+D$4)/($A8-D$4)/(1+$A8)^5-假设!$B$13+假设!$B$14-假设!$B$15)/假设!$B$16 | E8: =(SUMPRODUCT(预测!$B$13:$F$13/(1+$A8)^预测!$B$3:$F$3)+预测!$F$13*(1+E$4)/($A8-E$4)/(1+$A8)^5-假设!$B$13+假设!$B$14-假设!$B$15)/假设!$B$16 | F8: =(SUMPRODUCT(预测!$B$13:$F$13/(1+$A8)^预测!$B$3:$F$3)+预测!$F$13*(1+F$4)/($A8-F$4)/(1+$A8)^5-假设!$B$13+假设!$B$14-假设!$B$15)/假设!$B$16
A9: 0.0745 | B9: =(SUMPRODUCT(预测!$B$13:$F$13/(1+$A9)^预测!$B$3:$F$3)+预测!$F$13*(1+B$4)/($A9-B$4)/(1+$A9)^5-假设!$B$13+假设!$B$14-假设!$B$15)/假设!$B$16 | C9: =(SUMPRODUCT(预测!$B$13:$F$13/(1+$A9)^预测!$B$3:$F$3)+预测!$F$13*(1+C$4)/($A9-C$4)/(1+$A9)^5-假设!$B$13+假设!$B$14-假设!$B$15)/假设!$B$16 | D9: =(SUMPRODUCT(预测!$B$13:$F$13/(1+$A9)^预测!$B$3:$F$3)+预测!$F$13*(1+D$4)/($A9-D$4)/(1+$A9)^5-假设!$B$13+假设!$B$14-假设!$B$15)/假设!$B$16 | E9: =(SUMPRODUCT(预测!$B$13:$F$13/(1+$A9)^预测!$B$3:$F$3)+预测!$F$13*(1+E$4)/($A9-E$4)/(1+$A9)^5-假设!$B$13+假设!$B$14-假设!$B$15)/假设!$B$16 | F9: =(SUMPRODUCT(预测!$B$13:$F$13/(1+$A9)^预测!$B$3:$F$3)+预测!$F$13*(1+F$4)/($A9-F$4)/(1+$A9)^5-假设!$B$13+假设!$B$14-假设!$B$15)/假设!$B$16

Sheet WACC
A1: WACC 参考计算（CAPM）
A3: 无风险利率 rf | B3: 0.0165
A4: Beta（Blume 调整后） | B4: 0.87
A5: 股权风险溢价 ERP | B5: 0.06
A6: 税前债务成本 | B6: 0.0288
A7: 税率 | B7: 0.164
A8: 股权市值（亿元） | B8: 6574.6
A9: 有息负债（亿元） | B9: 674.80997
A10: 股权成本 = rf + β×ERP | B10: =B3+B4*B5
A11: 税后债务成本 | B11: =B6*(1-B7)
A12: 股权权重 | B12: =B8/(B8+B9)
A13: 债务权重 | B13: =B9/(B8+B9)
A14: WACC | B14: =B13*B10+B14*B11

Sheet 历史
A1: 历史财务（亿元，来源：akshare / 东方财富年报）
A2: 项目 | B2: 2020 | C2: 2021 | D2: 2022 | E2: 2023 | F2: 2024 | G2: 2025
A3: 营业总收入 | B3: 2857.0973 | C3: 3433.6083 | D3: 3457.0871 | E3: 3737.098 | F3: 4090.8427 | G3: 4585.0241
A4: 收入增速 | C4: 0.20178205 | D4: 0.0068379408 | E4: 0.080996219 | F4: 0.09465757 | G4: 0.12080186
A5: 毛利率 | B5: 0.23598369 | C5: 0.22340117 | D5: 0.24118233 | E5: 0.25588806 | F5: 0.26294012 | G5: 0.26272971
A6: EBIT | B6: 293.06102 | C6: 298.9345 | D6: 309.49133 | E6: 361.33821 | F6: 419.42116 | G6: 468.52373
A7: EBIT 利润率 | B7: 0.10257299 | C7: 0.08706133 | D7: 0.08952373 | E7: 0.096689518 | F7: 0.10252684 | G7: 0.10218566
A8: 有效税率 | B8: 0.13128656 | C8: 0.13945761 | D8: 0.14720535 | E8: 0.16217158 | F8: 0.1698988 | G8: 0.16134674
A9: 归母净利润 | B9: 272.22969 | C9: 285.7365 | D9: 295.53507 | E9: 337.19935 | F9: 385.37237 | G9: 439.45411
A10: ROE | B10: 0.23165279 | C10: 0.22883062 | D10: 0.20676152 | E10: 0.20702467 | F10: 0.17779574 | G10: 0.19686925
A11: 经营现金流 | B11: 295.57117 | C11: 350.91704 | D11: 346.57828 | E11: 579.02611 | F11: 605.11572 | G11: 533.4593
A12: 经营现金流 / 归母净利润 | B12: 1.0857419 | C12: 1.2281142 | D12: 1.1727146 | E12: 1.7171626 | F12: 1.5702104 | G12: 1.2139136
A13: 折旧摊销 / 收入 | B13: 0.017571176 | C13: 0.018006865 | D13: 0.018824866 | E13: 0.01966478 | F13: 0.019125253 | G13: 0.020370002
A14: 资本开支 / 收入 | B14: 0.016298297 | C14: 0.019878089 | D14: 0.021266792 | E14: 0.016895599 | F14: 0.019163866 | G14: 0.024300612
A15: 营运资本 / 收入 | B15: -0.12492102 | C15: -0.050712151 | D15: 0.024913876 | E15: -0.080576663 | F15: -0.096388843 | G15: 0.080800232
A16: FCFF | C16: 68.03492 | D16: -4.764499 | E16: 700.34045 | F16: 441.19275 | G16: -389.87559
A17: 现金 | B17: 1094.5008 | C17: 777.54758 | D17: 585.54692 | E17: 834.64434 | F17: 1473.4642 | G17: 859.57867
A18: 有息负债 | B18: 590.81397 | C18: 555.96735 | D18: 677.6715 | E18: 746.8091 | F18: 862.55072 | G18: 674.80997
