Workbook

Sheet 假设
A1: 招商银行 估值模型：PB-ROE 与 DDM（蓝色为输入假设）
A2: 项目 | B2: 数值 | C2: 依据
A3: 基期年份 | B3: 2025
A4: 每股普通股净资产 BVPS（元） | B4: 43.434496
A5: 基期每股收益 EPS（元） | B5: 5.9548374
A6: 长期可持续 ROE | B6: 0.145 | C6: 近3年ROE均值15.28%（2023 16.75%、2024 15.05%、2025 14.03%），呈持续下行趋势，故在均值下方取14.5%作为长期锚定值
A7: 股权成本 Ke | B7: 0.1 | C7: CAPM：rf 1.65% + Beta 0.80 × ERP 6% = 6.45%
A8: 永续增长率 g | B8: 0.03 | C8: 永续增长3%，为规则上限，且低于ROE与Ke
A9: 第一阶段 EPS 增速 g1 | B9: 0.0288 | C9: 第一阶段5年EPS增速锚定近3年归母净利润增速均值2.88%
A10: 第一阶段派息率 | B10: 0.3323 | C10: 派息率锚定近3年（2023-2025）均值33.23%
A11: 第一阶段年数 | B11: 5
A12: 当前股价（元） | B12: 43.05

Sheet 估值
A1: 估值汇总
A3: 合理 P/B =（ROE − g）/（Ke − g） | B3: =(假设!B6-假设!B8)/(假设!B7-假设!B8)
A4: PB-ROE 每股价值（元） | B4: =B3*假设!B4
A5: DDM 每股价值（元） | B5: =DDM!B13
A6: 两种方法平均（元） | B6: =AVERAGE(B4,B5)
A7: 当前股价（元） | B7: =假设!B12
A8: 当前 P/B | B8: =假设!B12/假设!B4
A9: 平均值相对现价 | B9: =B6/B7-1

Sheet DDM
A1: 两阶段股利贴现模型
A2: 期数 t | B2: EPS | C2: DPS | D2: 现值
A3: 1 | B3: =假设!$B$5*(1+假设!$B$9)^A3 | C3: =B3*假设!$B$10 | D3: =C3/(1+假设!$B$7)^A3
A4: 2 | B4: =假设!$B$5*(1+假设!$B$9)^A4 | C4: =B4*假设!$B$10 | D4: =C4/(1+假设!$B$7)^A4
A5: 3 | B5: =假设!$B$5*(1+假设!$B$9)^A5 | C5: =B5*假设!$B$10 | D5: =C5/(1+假设!$B$7)^A5
A6: 4 | B6: =假设!$B$5*(1+假设!$B$9)^A6 | C6: =B6*假设!$B$10 | D6: =C6/(1+假设!$B$7)^A6
A7: 5 | B7: =假设!$B$5*(1+假设!$B$9)^A7 | C7: =B7*假设!$B$10 | D7: =C7/(1+假设!$B$7)^A7
A9: 第二阶段派息率 = 1 − g / ROE | B9: =1-假设!B8/假设!B6
A10: 终值 | B10: =B7*(1+假设!B8)*B9/(假设!B7-假设!B8)
A11: 终值现值 | B11: =B10/(1+假设!B7)^假设!B11
A12: 第一阶段股利现值合计 | B12: =SUM(D3:D7)
A13: DDM 每股价值（元） | B13: =B12+B11

Sheet 敏感性
A1: PB-ROE 每股价值敏感性（行：Ke，列：g）
A4: Ke \ g | B4: 0.02 | C4: 0.025 | D4: 0.03 | E4: 0.035 | F4: 0.04
A5: 0.09 | B5: =(假设!$B$6-B$4)/($A5-B$4)*假设!$B$4 | C5: =(假设!$B$6-C$4)/($A5-C$4)*假设!$B$4 | D5: =(假设!$B$6-D$4)/($A5-D$4)*假设!$B$4 | E5: =(假设!$B$6-E$4)/($A5-E$4)*假设!$B$4 | F5: =(假设!$B$6-F$4)/($A5-F$4)*假设!$B$4
A6: 0.095 | B6: =(假设!$B$6-B$4)/($A6-B$4)*假设!$B$4 | C6: =(假设!$B$6-C$4)/($A6-C$4)*假设!$B$4 | D6: =(假设!$B$6-D$4)/($A6-D$4)*假设!$B$4 | E6: =(假设!$B$6-E$4)/($A6-E$4)*假设!$B$4 | F6: =(假设!$B$6-F$4)/($A6-F$4)*假设!$B$4
A7: 0.1 | B7: =(假设!$B$6-B$4)/($A7-B$4)*假设!$B$4 | C7: =(假设!$B$6-C$4)/($A7-C$4)*假设!$B$4 | D7: =(假设!$B$6-D$4)/($A7-D$4)*假设!$B$4 | E7: =(假设!$B$6-E$4)/($A7-E$4)*假设!$B$4 | F7: =(假设!$B$6-F$4)/($A7-F$4)*假设!$B$4
A8: 0.105 | B8: =(假设!$B$6-B$4)/($A8-B$4)*假设!$B$4 | C8: =(假设!$B$6-C$4)/($A8-C$4)*假设!$B$4 | D8: =(假设!$B$6-D$4)/($A8-D$4)*假设!$B$4 | E8: =(假设!$B$6-E$4)/($A8-E$4)*假设!$B$4 | F8: =(假设!$B$6-F$4)/($A8-F$4)*假设!$B$4
A9: 0.11 | B9: =(假设!$B$6-B$4)/($A9-B$4)*假设!$B$4 | C9: =(假设!$B$6-C$4)/($A9-C$4)*假设!$B$4 | D9: =(假设!$B$6-D$4)/($A9-D$4)*假设!$B$4 | E9: =(假设!$B$6-E$4)/($A9-E$4)*假设!$B$4 | F9: =(假设!$B$6-F$4)/($A9-F$4)*假设!$B$4

Sheet 历史
A1: 历史指标（亿元；每股为元）
A2: 项目 | B2: 2020 | C2: 2021 | D2: 2022 | E2: 2023 | F2: 2024 | G2: 2025
A3: 归母净利润 | B3: 973.42 | C3: 1199.22 | D3: 1380.12 | E3: 1466.02 | F3: 1483.91 | G3: 1501.81
A4: 利润增速 | C4: 0.23196565 | D4: 0.15084805 | E4: 0.062240965 | F4: 0.012203108 | G4: 0.012062726
A5: 普通股净资产 | B5: 6396.96 | C5: 7317.02 | D5: 8250.57 | E5: 9259.24 | F5: 10455.68 | G5: 10954.18
A6: BVPS | B6: 25.364631 | C6: 29.012768 | D6: 32.714393 | E6: 36.713878 | F6: 41.457891 | G6: 43.434496
A7: EPS | B7: 3.8597145 | C7: 4.7550357 | D7: 5.4723236 | E7: 5.8129262 | F7: 5.883862 | G7: 5.9548374
A8: ROE | C8: 0.17489015 | D8: 0.17730683 | E8: 0.16745127 | F8: 0.15053675 | G8: 0.14029144
A9: ROA | C9: 0.013619399 | D9: 0.014236897 | E9: 0.013851681 | F9: 0.012803078 | G9: 0.011908467
A10: 净利息收入占比 | B10: 0.63697923 | C10: 0.61559895 | D10: 0.63296334 | E10: 0.63301221 | F10: 0.62602818 | G10: 0.63873351
A11: 信用成本 | B11: 0.013502524 | C11: 0.012363105 | D11: 0.0097726012 | E11: 0.00660157 | F11: 0.0060272462 | G11: 0.0056517211
A12: 贷存比 | B12: 0.84820736 | C12: 0.83559316 | D12: 0.76504757 | E12: 0.75878363 | F12: 0.72129534 | G12: 0.7057481
A13: 权益乘数 | B13: 13.070971 | C13: 12.640421 | D13: 12.288741 | E13: 11.910786 | F13: 11.622425 | G13: 11.931996
A14: 当年派发每股股利 | B14: 1.2 | C14: 1.253 | D14: 1.522 | E14: 1.738 | F14: 1.972 | G14: 2
A15: 派息率（近似） | C15: 0.32463541 | D15: 0.32008172 | E15: 0.31759818 | F15: 0.33924394 | G15: 0.3399128
